tweet_getter/__init__.py
tweet_getter/__main__.py
tweet_getter/dataset_maker.py
utility/__init__.py
utility/utility.py
tweet_getter-1.0.0rc2.dist-info/LICENSE
tweet_getter-1.0.0rc2.dist-info/METADATA
tweet_getter-1.0.0rc2.dist-info/WHEEL
tweet_getter-1.0.0rc2.dist-info/top_level.txt
tweet_getter-1.0.0rc2.dist-info/RECORD
