Metadata-Version: 2.1
Name: tweet-getter
Version: 1.0.0rc2
Summary: Get Tweets by IDs through Twitter's API
Home-page: https://github.com/agn-7/tweet-getter
Author: agn-7
Author-email: benyaminjmf@gmail.com
License: MIT
Download-URL: https://github.com/agn-7/tweet-getter/archive/1.0.0rc2.zip
Keywords: tweets,twitter,twitter-api,tweepy,python,python-3,dataset,sentiment-analysis,emotion-detection,nlp,natural-language-processing
Platform: UNKNOWN
Classifier: Programming Language :: Python :: 3
Requires-Dist: tweepy
Requires-Dist: pandas
Requires-Dist: tqdm
Requires-Dist: easydict
